.gitignore
CHANGES.txt
LICENSE.txt
README.txt
setup.py
js/__init__.py
js.deform_bootstrap.egg-info/PKG-INFO
js.deform_bootstrap.egg-info/SOURCES.txt
js.deform_bootstrap.egg-info/dependency_links.txt
js.deform_bootstrap.egg-info/entry_points.txt
js.deform_bootstrap.egg-info/namespace_packages.txt
js.deform_bootstrap.egg-info/not-zip-safe
js.deform_bootstrap.egg-info/requires.txt
js.deform_bootstrap.egg-info/top_level.txt
js/deform_bootstrap/__init__.py
js/deform_bootstrap/test_deform_bootstrap.txt