Metadata-Version: 1.0
Name: js.deform-bootstrap
Version: 0.2.6
Summary: Fanstatic packaging of deform_bootstrap
Home-page: https://github.com/disko/js.deform_bootstrap
Author: Andreas Kaiser
Author-email: disko@binary-punks.com
License: BSD
Platform: UNKNOWN
